MANIFEST.in
README.md
README.rst
setup.cfg
setup.py
NanoFilt.egg-info/PKG-INFO
NanoFilt.egg-info/SOURCES.txt
NanoFilt.egg-info/dependency_links.txt
NanoFilt.egg-info/entry_points.txt
NanoFilt.egg-info/requires.txt
NanoFilt.egg-info/top_level.txt
nanofilt/NanoFilt.py
nanofilt/__init__.py
nanofilt/version.py
scripts/test.sh