Metadata-Version: 2.1
Name: NanoFilt
Version: 2.2.1
Summary: Filtering and trimming of Oxford Nanopore Sequencing data
Home-page: https://github.com/wdecoster/nanofilt
Author: Wouter De Coster
Author-email: decosterwouter@gmail.com
License: MIT
Keywords: nanopore sequencing processing trimming filtering
Platform: UNKNOWN
Classifier: Development Status :: 4 - Beta
Classifier: Intended Audience :: Science/Research
Classifier: Topic :: Scientific/Engineering :: Bio-Informatics
Classifier: License :: OSI Approved :: MIT License
Classifier: Programming Language :: Python :: 3
Classifier: Programming Language :: Python :: 3.3
Classifier: Programming Language :: Python :: 3.4
Classifier: Programming Language :: Python :: 3.5
Requires-Python: >=3
